<?xml version="1.0" encoding="UTF-8"?>
<objects serializationModel="Studio.02.01.00">
	<object class="AudioFile" id="{e75903bf-6e09-44bc-a279-54f4c77150eb}">
		<property name="assetPath">
			<value>Sound effects/99 Sound Effects/WAV/Retro - Magic Respawn.wav</value>
		</property>
		<property name="frequencyInKHz">
			<value>96</value>
		</property>
		<property name="channelCount">
			<value>1</value>
		</property>
		<property name="length">
			<value>1.2476041666666666</value>
		</property>
		<relationship name="masterAssetFolder">
			<destination>{84cdb71f-7808-4e04-a04d-8fe895f6d6e6}</destination>
		</relationship>
	</object>
</objects>
